HDL_SRC/CORE/alu/alu.v
/*
 * *****************************************************************
 * File: alu.v
 * Category: alu
 * File Created: 2018/12/19 23:48
 * Author: Takuya Shono ( ta.shono+1@gmail.com )
 * *****
 * Last Modified: 2018/12/24 24:43
 * Modified By: Takuya Shono ( ta.shono+1@gmail.com )
 * *****
 * Copyright 2018 - 2018  Project RockWave
 * *****************************************************************
 * Description:
 *   
 * *****************************************************************
 * HISTORY:
 * Date      	By        	Comments
 * ----------	----------	----------------------------------------
 * 2018/12/19	Takuya Shono	First Version
 * *****************************************************************
 */

module alu (
    aluin1,
    aluin2,
    funct3,
    aluout
    );
    
    parameter XLEN = 32;

    input  wire [XLEN-1:0] aluin1;
    input  wire [XLEN-1:0] aluin2;
    input  wire [2:0] funct3;
    output wire [XLEN-1:0] aluout;

    function [XLEN-1:0] calc( 
        input [2:0] funct3,
        input [XLEN-1:0] aluin1,
        input [XLEN-1:0] aluin2
        );        
        begin
            case( funct3 )
                    3'b000  : calc = aluin1 + aluin2; //ADD 加算
 //                   3'b000  : calc = aluin1 - aluin2; //SUB 減算
                    3'b001  : calc = aluin1 + aluin2; //SLL 左シフト
                    3'b010  : calc = aluin1 + aluin2; //SLT 符号付きで大小比較＆結果をレジスタにロード
                    3'b011  : calc = aluin1 + aluin2; //SLTU 符号なしで大小比較＆結果をレジスタにロード
                    3'b100  : calc = aluin1 ^ aluin2; //排他的論理和
 //                   3'b101  : calc = aluin1 + aluin2; //右論理シフト
 //                   3'b101  : calc = aluin1 + aluin2; //左論理シフト
                    3'b110  : calc = aluin1 | aluin2; //OR 論理和                   
                    3'b111  : calc = aluin1 & aluin2; //論理積
            endcase
        end
    endfunction

    assign aluout = calc( funct3, aluin1, aluin2 );

endmodule // alu

HDL_SIM/CORE/alu/alu_tb.v
 /*
 * *****************************************************************
 * File: alu_tb.v
 * Category: alu
 * File Created: 2018/12/19 12:12
 * Author: Takuya Shono ( ta.shono+1@gmail.com )
 * *****
 * Last Modified: 2018/12/19 12:12
 * Modified By: Takuya Shono ( ta.shono+1@gmail.com )
 * *****
 * Copyright 2018 - 2018  Project RockWave
 * *****************************************************************
 * Description:
 *   
 * *****************************************************************
 * HISTORY:
 * Date      	By        	Comments
 * ----------	----------	----------------------------------------
 * 2018/12/19	Takuya Shono	First Version
 * *****************************************************************
 */

module alu_tb;

reg [31:0] aluin1;
reg [31:0] aluin2;
reg [2:0] funct3;
wire [31:0] aluout;

//1周期1000unit
parameter STEP = 1;

alu test(
   aluin1, aluin2, funct3, aluout
);

initial begin

    funct3 = 3'b000;
    aluin1 = 32'b0000_0000_0000_0000_0000_0000_0000_0000;
    aluin2 = 32'b0000_0000_0000_0000_0000_0000_0000_0000;

    #STEP
    funct3 = 3'b000;
    aluin1 = 32'b0000_0000_0000_0000_0000_0000_0000_0000;
    aluin2 = 32'b0000_0000_0000_0000_0000_0000_0000_0000;

    #STEP
    funct3 = 3'b000;
    aluin1 = 32'b0000_0000_0000_0000_0000_0000_0000_0111;
    aluin2 = 32'b0000_0000_0000_0000_0000_0000_0000_1010;

    #STEP    funct3 = 3'b001;
    #STEP    funct3 = 3'b010;
    #STEP    funct3 = 3'b011;    
    #STEP    funct3 = 3'b100;
    #STEP    funct3 = 3'b101;
    #STEP    funct3 = 3'b110;
    #STEP    funct3 = 3'b111;


end

/* 表示 */
initial begin
 $dumpfile("alu.vcd");
    $dumpvars(0,alu_tb);
    $monitor(" STEP=%d funct3= %b aluin1=%b  aluin2=%b aluout=%b ",STEP,funct3,aluin1,aluin2,aluout);
end

endmodule

HDL_SIM/CORE/alu/alu.vcd
$date
	Mon Dec 24 02:39:34 2018
$end
$version
	Icarus Verilog
$end
$timescale
	1s
$end
$scope module alu_tb $end
$var wire 32 ! aluout [31:0] $end
$var reg 32 " aluin1 [31:0] $end
$var reg 32 # aluin2 [31:0] $end
$var reg 3 $ funct3 [2:0] $end
$scope module test $end
$var wire 32 % aluin1 [31:0] $end
$var wire 32 & aluin2 [31:0] $end
$var wire 3 ' funct3 [2:0] $end
$var wire 32 ( aluout [31:0] $end
$scope function calc $end
$var reg 32 ) aluin1 [31:0] $end
$var reg 32 * aluin2 [31:0] $end
$var reg 32 + calc [31:0] $end
$var reg 3 , funct3 [2:0] $end
$upscope $end
$upscope $end
$upscope $end
$enddefinitions $end
#0
$dumpvars
b0 ,
b0 +
b0 *
b0 )
b0 (
b0 '
b0 &
b0 %
b0 $
b0 #
b0 "
b0 !
$end
#2
b10001 !
b10001 (
b10001 +
b1010 *
b111 )
b1010 #
b1010 &
b111 "
b111 %
#3
b1 ,
b1 $
b1 '
#4
b10 ,
b10 $
b10 '
#5
b11 ,
b11 $
b11 '
#6
b1101 !
b1101 (
b1101 +
b100 ,
b100 $
b100 '
#7
b101 ,
b101 $
b101 '
#8
b1111 !
b1111 (
b1111 +
b110 ,
b110 $
b110 '
#9
b10 !
b10 (
b10 +
b111 ,
b111 $
b111 '
